castxml_patch/__init__.py
castxml_patch/_version.py
castxml_patch/data/bin/castxml.exe
castxml_patch/data/share/castxml/detect_vs.c
castxml_patch/data/share/castxml/detect_vs.cpp
castxml_patch/data/share/castxml/empty.c
castxml_patch/data/share/castxml/empty.cpp
castxml_patch/data/share/castxml/clang/include/__clang_cuda_builtin_vars.h
castxml_patch/data/share/castxml/clang/include/__clang_cuda_cmath.h
castxml_patch/data/share/castxml/clang/include/__clang_cuda_complex_builtins.h
castxml_patch/data/share/castxml/clang/include/__clang_cuda_device_functions.h
castxml_patch/data/share/castxml/clang/include/__clang_cuda_intrinsics.h
castxml_patch/data/share/castxml/clang/include/__clang_cuda_libdevice_declares.h
castxml_patch/data/share/castxml/clang/include/__clang_cuda_math.h
castxml_patch/data/share/castxml/clang/include/__clang_cuda_math_forward_declares.h
castxml_patch/data/share/castxml/clang/include/__clang_cuda_runtime_wrapper.h
castxml_patch/data/share/castxml/clang/include/__clang_hip_cmath.h
castxml_patch/data/share/castxml/clang/include/__clang_hip_libdevice_declares.h
castxml_patch/data/share/castxml/clang/include/__clang_hip_math.h
castxml_patch/data/share/castxml/clang/include/__clang_hip_runtime_wrapper.h
castxml_patch/data/share/castxml/clang/include/__stddef_max_align_t.h
castxml_patch/data/share/castxml/clang/include/__wmmintrin_aes.h
castxml_patch/data/share/castxml/clang/include/__wmmintrin_pclmul.h
castxml_patch/data/share/castxml/clang/include/adxintrin.h
castxml_patch/data/share/castxml/clang/include/altivec.h
castxml_patch/data/share/castxml/clang/include/ammintrin.h
castxml_patch/data/share/castxml/clang/include/amxintrin.h
castxml_patch/data/share/castxml/clang/include/arm64intr.h
castxml_patch/data/share/castxml/clang/include/arm_acle.h
castxml_patch/data/share/castxml/clang/include/arm_bf16.h
castxml_patch/data/share/castxml/clang/include/arm_cde.h
castxml_patch/data/share/castxml/clang/include/arm_cmse.h
castxml_patch-0.5.0a0.dist-info/METADATA
castxml_patch-0.5.0a0.dist-info/WHEEL
castxml_patch-0.5.0a0.dist-info/entry_points.txt
castxml_patch-0.5.0a0.dist-info/top_level.txt
castxml_patch-0.5.0a0.dist-info/RECORD
